ml_som/__init__.py
ml_som/text_reader.py
ml_som/data/my_code.py
ml_som-0.1.dist-info/METADATA
ml_som-0.1.dist-info/WHEEL
ml_som-0.1.dist-info/top_level.txt
ml_som-0.1.dist-info/RECORD
