Metadata-Version: 2.1
Name: ml-som
Version: 0.1
Summary: Code for SOM on Credit Card Dataset
Home-page: https://github.com/savioratharv/prac_testing
Author: davinci003
Author-email: freegpt00@gmail.com
